[
  {
    "rank": 1,
    "foundation_ein": "222648036",
    "foundation_name": "THE MAXIMILIAN E AND MARION O HOFFMAN",
    "foundation_state": "CT",
    "match_score": 100.0,
    "match_probability": 0.999928438635732,
    "same_state": true,
    "fit_score": 10,
    "effort": "Medium",
    "status": "HIGH",
    "quality_tier": "strict",
    "amount_min": 25000.0,
    "amount_max": 75000.0,
    "funder_snapshot": {
      "annual_giving": {
        "total": 1896750.0,
        "count": 50,
        "year": 2023
      },
      "typical_grant": {
        "median": 20000.0,
        "min": 2500.0,
        "max": 500000.0,
        "avg": 41223.50993377483
      },
      "geographic_focus": {
        "top_state": "CT",
        "top_state_pct": 0.947,
        "in_state_pct": 0.947,
        "foundation_state": "CT"
      },
      "repeat_funding": {
        "unique": 134,
        "repeat": 17,
        "rate": 0.127
      },
      "giving_style": {
        "general_pct": 0.748,
        "program_pct": 0.252
      },
      "recipient_profile": {
        "budget_min": 662463,
        "budget_max": 7530231,
        "budget_median": 2883821,
        "primary_sector": "A",
        "primary_sector_pct": 0.181
      },
      "funding_trend": {
        "direction": "Declining",
        "change_pct": -0.161,
        "oldest_year": 2020,
        "newest_year": 2023
      },
      "comparable_grant": {
        "recipient": "QUINNIPIAC UNIVERSITY",
        "amount": 50000.0,
        "purpose": "HOFFMAN SCHOLARS FUND",
        "year": 2023
      },
      "contact": {
        "website_url": "https://www.westhartfordct.gov",
        "phone": "8605212949",
        "email": null,
        "app_contact_name": "MARION BARRAK",
        "app_contact_phone": "8605212949",
        "app_contact_email": null,
        "deadlines": "YES",
        "restrictions": "NONE OTHER THAN POLITICAL LIMITATIONS",
        "how_to_apply": "PRESCRIBED APPLICATION FORM WHICH MAY BE OBTAINED FROM THE FOUNDATION"
      },
      "officers": [
        {
          "name": "Marion L Barrak",
          "title": "President/Director",
          "compensation": 150480.0
        }
      ],
      "foundation_ein": "222648036",
      "foundation_name": "THE MAXIMILIAN E AND MARION O HOFFMAN",
      "match_score": 100.0,
      "match_rank": 225
    },
    "comparable_grant": {
      "recipient": "QUINNIPIAC UNIVERSITY",
      "amount": 50000.0,
      "purpose": "HOFFMAN SCHOLARS FUND",
      "year": 2023
    },
    "connections": [
      {
        "type": "shared_funder",
        "description": "The Tudor Foundation Inc has funded both you and their grantees",
        "strength": "moderate",
        "funder_name": "The Tudor Foundation Inc",
        "funder_ein": "061502288"
      },
      {
        "type": "shared_funder",
        "description": "NEWMAN'S OWN FOUNDATION has funded both you and their grantees",
        "strength": "moderate",
        "funder_name": "NEWMAN'S OWN FOUNDATION",
        "funder_ein": "061606588"
      },
      {
        "type": "shared_funder",
        "description": "NEW YORK LIFE FOUNDATION has funded both you and their grantees",
        "strength": "moderate",
        "funder_name": "NEW YORK LIFE FOUNDATION",
        "funder_ein": "132989476"
      },
      {
        "type": "geographic",
        "description": "Both based in CT",
        "strength": "strong"
      },
      {
        "type": "sector_alignment",
        "description": "Foundation funds 17% Education organizations",
        "strength": "moderate",
        "sector": "B",
        "percentage": 0.173
      }
    ],
    "deadline": "Rolling",
    "portal_url": "Contact foundation directly for application form",
    "contact_name": "Marion L Barrak",
    "contact_email": "",
    "contact_phone": "860-521-2949",
    "application_requirements": [],
    "why_this_fits": "",
    "positioning_strategy": "",
    "next_steps": [],
    "viability": {
      "tier": "ready",
      "tier_reason": "Strong fit with open application",
      "multiplier": 0.95,
      "adjusted_score": 9.5,
      "unsolicited_status": "open",
      "unsolicited_reason": "Online application available",
      "fit_rating_enriched": "strong",
      "red_flags": [
        "Declining giving trend (-16.1% over 2020-2023)",
        "Low repeat funding rate (12.7%) suggests one-time funding more likely than multi-year support",
        "Unclear application process - no online application portal found; must contact directly"
      ],
      "recommendation": ""
    },
    "current_opportunities": [
      {
        "name": "Education and Community Support Grants",
        "deadline": "Rolling basis; applications reviewed quarterly",
        "amount_min": 2500,
        "amount_max": 500000,
        "focus": "Education, health, human services in central Connecticut and Hartford area",
        "url": "https://fconline.foundationcenter.org/fdo-grantmaker-profile?key=HOFF021"
      }
    ],
    "foundation_priorities": [
      "Education programs in Hartford/central Connecticut",
      "Nonprofit support in CT",
      "Community development in West Hartford area",
      "Historically supported: scholarships, university programs"
    ]
  },
  {
    "rank": 2,
    "foundation_ein": "301214067",
    "foundation_name": "ELISABETH C DELUCA FOUNDATION INC",
    "foundation_state": "FL",
    "match_score": 100.0,
    "match_probability": 0.9999839601166054,
    "same_state": false,
    "fit_score": 10,
    "effort": "High",
    "status": "MEDIUM",
    "quality_tier": "strict",
    "amount_min": 4900000.0,
    "amount_max": 14700000.0,
    "funder_snapshot": {
      "annual_giving": {
        "total": 13980500.0,
        "count": 14,
        "year": 2023
      },
      "typical_grant": {
        "median": 125000.0,
        "min": 10000.0,
        "max": 9800000.0,
        "avg": 696270.8333333334
      },
      "geographic_focus": {
        "top_state": "CT",
        "top_state_pct": 0.792,
        "in_state_pct": 0.042,
        "foundation_state": "FL"
      },
      "repeat_funding": {
        "unique": 18,
        "repeat": 6,
        "rate": 0.333
      },
      "giving_style": {
        "general_pct": 0.083,
        "program_pct": 0.917
      },
      "recipient_profile": {
        "budget_min": 1412959,
        "budget_max": 43863263,
        "budget_median": 6649468,
        "primary_sector": "B",
        "primary_sector_pct": 0.333
      },
      "funding_trend": {
        "direction": "Growing",
        "change_pct": 4.121,
        "oldest_year": 2022,
        "newest_year": 2023
      },
      "comparable_grant": {
        "recipient": "UNIVERSITY OF CONNECTICUT FOUNDATION INC",
        "amount": 9800000.0,
        "purpose": "TO TRANSFORM LIVES BY PROVIDING RESOURCES FOR STUDENT SCHOLARSHIPS, FUNDING THE RESEARCH OF OUR RENOWNED SCHOLARS AND PROFESSORS, FACILITATING THE DISCOVERY OF INNOVATIVE TREATMENTS AND CURES FOR DISEASES, AND DRIVING ECONOMIC DEVELOPMENT THAT MAKES A POSITIVE DIFFERENCE THROUGHOUT CONNECTICUT",
        "year": 2023
      },
      "contact": {
        "website_url": "https://www.delucafdn.org",
        "phone": "9544952309",
        "email": null,
        "app_contact_name": null,
        "app_contact_phone": null,
        "app_contact_email": null,
        "deadlines": null,
        "restrictions": null,
        "how_to_apply": null
      },
      "officers": [
        {
          "name": "Elisabeth Deluca",
          "title": "President",
          "compensation": 0.0
        }
      ],
      "foundation_ein": "301214067",
      "foundation_name": "ELISABETH C DELUCA FOUNDATION INC",
      "match_score": 100.0,
      "match_rank": 188
    },
    "comparable_grant": {
      "recipient": "UNIVERSITY OF CONNECTICUT FOUNDATION INC",
      "amount": 9800000.0,
      "purpose": "TO TRANSFORM LIVES BY PROVIDING RESOURCES FOR STUDENT SCHOLARSHIPS, FUNDING THE RESEARCH OF OUR RENOWNED SCHOLARS AND PROFESSORS, FACILITATING THE DISCOVERY OF INNOVATIVE TREATMENTS AND CURES FOR DISEASES, AND DRIVING ECONOMIC DEVELOPMENT THAT MAKES A POSITIVE DIFFERENCE THROUGHOUT CONNECTICUT",
      "year": 2023
    },
    "connections": [
      {
        "type": "shared_funder",
        "description": "The Tudor Foundation Inc has funded both you and their grantees",
        "strength": "moderate",
        "funder_name": "The Tudor Foundation Inc",
        "funder_ein": "061502288"
      },
      {
        "type": "shared_funder",
        "description": "NEWMAN'S OWN FOUNDATION has funded both you and their grantees",
        "strength": "moderate",
        "funder_name": "NEWMAN'S OWN FOUNDATION",
        "funder_ein": "061606588"
      },
      {
        "type": "shared_funder",
        "description": "THE PITNEY BOWES FOUNDATION has funded both you and their grantees",
        "strength": "moderate",
        "funder_name": "THE PITNEY BOWES FOUNDATION",
        "funder_ein": "200523317"
      },
      {
        "type": "sector_alignment",
        "description": "Foundation funds 40% Education organizations",
        "strength": "strong",
        "sector": "B",
        "percentage": 0.4
      }
    ],
    "deadline": "RFP published on website; check for current deadline",
    "portal_url": "https://www.delucafdn.org/",
    "contact_name": "Elisabeth DeLuca",
    "contact_email": "",
    "contact_phone": "954-495-2309",
    "application_requirements": [],
    "why_this_fits": "",
    "positioning_strategy": "",
    "next_steps": [],
    "viability": {
      "tier": "conditional",
      "tier_reason": "RFP-based - monitor for open opportunities",
      "multiplier": 0.6,
      "adjusted_score": 6.0,
      "unsolicited_status": "conditional",
      "unsolicited_reason": "RFP-based only - must wait for specific solicitations",
      "fit_rating_enriched": "moderate",
      "red_flags": [
        "Does NOT accept unsolicited applications; must wait for RFP",
        "Geographic focus is primarily Florida (Pompano Beach HQ), though significant Connecticut giving exists",
        "Grant sizes ($125K+ median) are much larger than Horizons typical ask; may be overqualified",
        "No published application process or deadlines found",
        "Does not appear to have K-8 enrichment as explicit priority (higher ed focus)"
      ],
      "recommendation": ""
    },
    "deadline_source": "enrichment",
    "current_opportunities": [
      {
        "name": "Community Funding RFP (Grantee re-granting program)",
        "deadline": "RFP published on website; check for current deadline",
        "amount_min": 50000,
        "amount_max": 9800000,
        "focus": "Youth and Families, Economic Mobility in Florida (Miami-Dade, Broward, Palm Beach counties)",
        "url": "https://www.delucafdn.org/"
      },
      {
        "name": "Education and Nursing Programs",
        "deadline": "Rolling/Invitational",
        "amount_min": 10000,
        "amount_max": 40000000,
        "focus": "Higher education, nursing programs, education initiatives in CT",
        "url": "https://www.delucafdn.org/"
      }
    ],
    "foundation_priorities": [
      "Youth and Families programs",
      "Economic Mobility initiatives",
      "Education (primarily higher education and nursing)",
      "Health and healthcare workforce development",
      "Arts initiatives"
    ]
  },
  {
    "rank": 3,
    "foundation_ein": "131684331",
    "foundation_name": "THE FORD FOUNDATION",
    "foundation_state": "NY",
    "match_score": 100.0,
    "match_probability": 0.9999991864571272,
    "same_state": false,
    "fit_score": 10,
    "effort": "High",
    "status": "MEDIUM",
    "quality_tier": "strict",
    "amount_min": 375000.0,
    "amount_max": 1125000.0,
    "funder_snapshot": {
      "annual_giving": {
        "total": 735763273.0,
        "count": 3718,
        "year": 2023
      },
      "typical_grant": {
        "median": 100000.0,
        "min": 36.0,
        "max": 10000000,
        "avg": 208194.51456128265
      },
      "geographic_focus": {
        "top_state": "NY",
        "top_state_pct": 0.271,
        "in_state_pct": 0.271,
        "foundation_state": "NY"
      },
      "repeat_funding": {
        "unique": 7542,
        "repeat": 3346,
        "rate": 0.444
      },
      "giving_style": {
        "general_pct": 0.234,
        "program_pct": 0.766
      },
      "recipient_profile": {
        "budget_min": 1082292,
        "budget_max": 16066956,
        "budget_median": 3889823,
        "primary_sector": "A",
        "primary_sector_pct": 0.202
      },
      "funding_trend": {
        "direction": "Stable",
        "change_pct": -0.033,
        "oldest_year": 2020,
        "newest_year": 2023
      },
      "comparable_grant": {
        "recipient": "YALE UNIVERSITY",
        "amount": 750000.0,
        "purpose": "CORE SUPPORT FOR THE CENTER FOR PUBLIC THEOLOGY AND PUBLIC POLICY",
        "year": 2023
      },
      "contact": {
        "website_url": "https://WWW.FORDFOUNDATION.ORG",
        "phone": "2125735000",
        "email": null,
        "app_contact_name": "THE FORD FOUNDATION",
        "app_contact_phone": "2125735000",
        "app_contact_email": null,
        "deadlines": null,
        "restrictions": "ACTIVITIES SUPPORTED BY FOUNDATION GRANTS MUST BE CHARITABLE, EDUCATIONAL OR SCIENTIFIC UNDER THE PROVISIONS OF THE U.S. INTERNAL REVENUE CODE AND THE TREASURY REGULATIONS.",
        "how_to_apply": "PROPOSALS SHOULD SET FORTH A DESCRIPTION OF THE PROPOSED WORK; HOW THE WORK WILL BE CONDUCTED; THE NAMES AND CURRICULUM VITAE OF THOSE ENGAGED IN THE PROJECT; A DETAILED BUDGET, THE PROJECT'S PRESENT MEANS OF SUPPORT, THE PROJECT'S STATUS OF APPLICATIONS TO OTHER FUNDING SOURCES, AND THE PROJECT'S LEGAL AND TAX STATUS."
      },
      "officers": [
        {
          "name": "Eric W Doppstadt",
          "title": "Vp & Chief Investment Officer",
          "compensation": 4543917.0
        }
      ],
      "foundation_ein": "131684331",
      "foundation_name": "THE FORD FOUNDATION",
      "match_score": 100.0,
      "match_rank": 121
    },
    "comparable_grant": {
      "recipient": "YALE UNIVERSITY",
      "amount": 750000.0,
      "purpose": "CORE SUPPORT FOR THE CENTER FOR PUBLIC THEOLOGY AND PUBLIC POLICY",
      "year": 2023
    },
    "connections": [
      {
        "type": "shared_funder",
        "description": "The Tudor Foundation Inc has funded both you and their grantees",
        "strength": "moderate",
        "funder_name": "The Tudor Foundation Inc",
        "funder_ein": "061502288"
      },
      {
        "type": "shared_funder",
        "description": "THE KITE KEY FOUNDATION has funded both you and their grantees",
        "strength": "moderate",
        "funder_name": "THE KITE KEY FOUNDATION",
        "funder_ein": "061518993"
      },
      {
        "type": "shared_funder",
        "description": "NEWMAN'S OWN FOUNDATION has funded both you and their grantees",
        "strength": "moderate",
        "funder_name": "NEWMAN'S OWN FOUNDATION",
        "funder_ein": "061606588"
      },
      {
        "type": "geographic",
        "description": "Foundation in NY, adjacent to your CT",
        "strength": "moderate"
      },
      {
        "type": "sector_alignment",
        "description": "Foundation funds 14% Education organizations",
        "strength": "moderate",
        "sector": "B",
        "percentage": 0.137
      }
    ],
    "deadline": "NYC Good Neighbor: Late Summer/Early Fall 2025",
    "portal_url": "Submit through designated program portals only when open",
    "contact_name": "Eric W Doppstadt",
    "contact_email": "",
    "contact_phone": "212-573-5000",
    "application_requirements": [],
    "why_this_fits": "",
    "positioning_strategy": "",
    "next_steps": [],
    "viability": {
      "tier": "watch",
      "tier_reason": "Does not accept unsolicited proposals",
      "multiplier": 0.2,
      "adjusted_score": 2.0,
      "unsolicited_status": "closed",
      "unsolicited_reason": "Foundation does not accept unsolicited proposals",
      "fit_rating_enriched": "moderate",
      "red_flags": [
        "Does not accept unsolicited proposals - must be invited to specific programs",
        "No K-8 enrichment programs identified; education focus is primarily higher education and diversity in academia",
        "Geographic focus is NY (27% of giving), not CT",
        "High effort to secure: very competitive, limited open opportunities",
        "Last major education program (Ford Fellowships) ended in 2025"
      ],
      "recommendation": ""
    },
    "deadline_source": "enrichment",
    "current_opportunities": [
      {
        "name": "NYC Good Neighbor Committee Grants",
        "deadline": "Late Summer/Early Fall 2025",
        "amount_min": 36,
        "amount_max": 10000000,
        "focus": "Local NYC organizations addressing inequality",
        "url": "https://www.fordfoundation.org/work/our-grants/grant-opportunities/"
      },
      {
        "name": "JustFilms",
        "deadline": "Currently Closed",
        "amount_min": null,
        "amount_max": null,
        "focus": "Documentary film production and free expression",
        "url": "https://www.fordfoundation.org/work/our-grants/grant-opportunities/"
      }
    ],
    "foundation_priorities": [
      "Civic engagement and democratic participation",
      "Racial justice and equity",
      "Disability rights",
      "Climate justice",
      "Technology and governance"
    ]
  }
]